bpyutils/VERSION
bpyutils/__attr__.py
bpyutils/__init__.py
bpyutils/__main__.py
bpyutils/_compat.py
bpyutils/cache.py
bpyutils/config.py
bpyutils/const.py
bpyutils/db.py
bpyutils/exception.py
bpyutils/limits.py
bpyutils/log.py
bpyutils/parallel.py
bpyutils/psy.py
bpyutils/table.py
bpyutils/tree.py
bpyutils/__pycache__/__attr__.cpython-310.pyc
bpyutils/__pycache__/__init__.cpython-310.pyc
bpyutils/__pycache__/_compat.cpython-310.pyc
bpyutils/__pycache__/exception.cpython-310.pyc
bpyutils/__pycache__/log.cpython-310.pyc
bpyutils/api/__init__.py
bpyutils/api/base.py
bpyutils/api/github.py
bpyutils/cli/__init__.py
bpyutils/cli/formatter.py
bpyutils/cli/parser.py
bpyutils/cli/util.py
bpyutils/cli/__pycache__/__init__.cpython-310.pyc
bpyutils/cli/__pycache__/formatter.cpython-310.pyc
bpyutils/cli/__pycache__/parser.cpython-310.pyc
bpyutils/cli/__pycache__/util.cpython-310.pyc
bpyutils/commands/__init__.py
bpyutils/commands/util/__init__.py
bpyutils/data/bootstrap.sql
bpyutils/i18n/__init__.py
bpyutils/i18n/es.json
bpyutils/i18n/util.py
bpyutils/jobs/__init__.py
bpyutils/model/__init__.py
bpyutils/model/base.py
bpyutils/request/__init__.py
bpyutils/request/response.py
bpyutils/util/__init__.py
bpyutils/util/_csv.py
bpyutils/util/_dict.py
bpyutils/util/_json.py
bpyutils/util/array.py
bpyutils/util/cli.py
bpyutils/util/datetime.py
bpyutils/util/doc.py
bpyutils/util/environ.py
bpyutils/util/error.py
bpyutils/util/git.py
bpyutils/util/imports.py
bpyutils/util/jobs.py
bpyutils/util/ml.py
bpyutils/util/proxy.py
bpyutils/util/request.py
bpyutils/util/string.py
bpyutils/util/system.py
bpyutils/util/test.py
bpyutils/util/types.py
bpyutils/util/__pycache__/__init__.cpython-310.pyc
bpyutils/util/__pycache__/_dict.cpython-310.pyc
bpyutils/util/__pycache__/array.cpython-310.pyc
bpyutils/util/__pycache__/cli.cpython-310.pyc
bpyutils/util/__pycache__/environ.cpython-310.pyc
bpyutils/util/__pycache__/git.cpython-310.pyc
bpyutils/util/__pycache__/string.cpython-310.pyc
bpyutils-0.5.7.dist-info/AUTHORS.md
bpyutils-0.5.7.dist-info/LICENSE
bpyutils-0.5.7.dist-info/METADATA
bpyutils-0.5.7.dist-info/WHEEL
bpyutils-0.5.7.dist-info/entry_points.txt
bpyutils-0.5.7.dist-info/top_level.txt
bpyutils-0.5.7.dist-info/RECORD
